crams_contact/__init__.py
crams_contact/admin.py
crams_contact/apps.py
crams_contact/asgi.py
crams_contact/crams_api_urls.py
crams_contact/model_validators.py
crams_contact/models.py
crams_contact/permissions.py
crams_contact/settings.py
crams_contact/test_utils.py
crams_contact/urls.py
crams_contact/wsgi.py
crams_contact/auth/__init__.py
crams_contact/auth/auth_api.py
crams_contact/auth/crams_token_auth.py
crams_contact/auth/rapidconnect_auth.py
crams_contact/auth/user_roles_api.py
crams_contact/config/__init__.py
crams_contact/config/contact_config.py
crams_contact/migrations/0001_initial.py
crams_contact/migrations/0002_load_contact_initial.py
crams_contact/migrations/0003_contactlog.py
crams_contact/migrations/__init__.py
crams_contact/serializers/__init__.py
crams_contact/serializers/base_contact_serializer.py
crams_contact/serializers/contact_erb_roles.py
crams_contact/serializers/contact_id_sz.py
crams_contact/serializers/contact_role.py
crams_contact/serializers/contact_serializer.py
crams_contact/serializers/crams_role_init.py
crams_contact/serializers/lookup_serializers.py
crams_contact/serializers/organisation_serializers.py
crams_contact/serializers/role_free_contact_serializer.py
crams_contact/serializers/util_sz.py
crams_contact/sqls/__init__.py
crams_contact/sqls/contact_initial.sql
crams_contact/sqls/notify_contact_roles.mysql.sql
crams_contact/utils/__init__.py
crams_contact/utils/contact_utils.py
crams_contact/utils/validators.py
crams_contact/views/__init__.py
crams_contact/views/contact.py
crams_contact/views/contact_role.py
crams_contact/views/organisation.py
crams_manager/__init__.py
crams_manager/admin.py
crams_manager/apps.py
crams_manager/models.py
crams_manager/tests.py
crams_manager/views.py
crams_manager/migrations/0001_initial.py
crams_manager/migrations/__init__.py
crams_contact-1.0.2.1.dist-info/METADATA
crams_contact-1.0.2.1.dist-info/WHEEL
crams_contact-1.0.2.1.dist-info/top_level.txt
crams_contact-1.0.2.1.dist-info/RECORD
